README
setup.cfg
setup.py
FireInFolders.egg-info/PKG-INFO
FireInFolders.egg-info/SOURCES.txt
FireInFolders.egg-info/dependency_links.txt
FireInFolders.egg-info/entry_points.txt
FireInFolders.egg-info/not-zip-safe
FireInFolders.egg-info/top_level.txt
fire_in_folders/__init__.py