Metadata-Version: 1.0
Name: FireInFolders
Version: 0.2
Summary: Command line utility which excecutes commands in multiple folders
Home-page: http://www.niteoweb.com/
Author: niteoweb
Author-email: info@niteoweb.com
License: BSD
Keywords: util cli
Platform: UNKNOWN
